MoConfig/__init__.py
MoConfig/config.py
moconfig-1.0.10.dist-info/METADATA
moconfig-1.0.10.dist-info/WHEEL
moconfig-1.0.10.dist-info/top_level.txt
moconfig-1.0.10.dist-info/RECORD
