Metadata-Version: 2.4
Name: MoConfig
Version: 1.0.10
Summary: A person config class
Author: DriftCloud
Author-email: mo7984130@qq.com
Dynamic: author
Dynamic: author-email
Dynamic: summary
